README.txt
release_howto.txt
setup.cfg
setup.py
TurboJson.egg-info/PKG-INFO
TurboJson.egg-info/SOURCES.txt
TurboJson.egg-info/dependency_links.txt
TurboJson.egg-info/entry_points.txt
TurboJson.egg-info/not-zip-safe
TurboJson.egg-info/requires.txt
TurboJson.egg-info/top_level.txt
turbojson/__init__.py
turbojson/jsonify.py
turbojson/jsonsupport.py
turbojson/prioritized_methods.py
turbojson/tests/__init__.py
turbojson/tests/test_jsonify.py
turbojson/tests/test_prioritized_methods.py
turbojson/tests/test_sqlalchemy.py
turbojson/tests/test_sqlobject.py